{"_ts":[1530455109],"_r":{"breakdown":{"html":{"bytes":[69979],"requests":[16]},"js":{"bytes":[1100710],"requests":[20]},"css":{"bytes":[139943],"requests":[3]},"image":{"bytes":[21303],"requests":[38]},"flash":{"bytes":[0],"requests":[0]},"font":{"bytes":[112252],"requests":[5]},"other":{"bytes":[8024],"requests":[27]}},"date":[1530455109],"domElements":[1021],"domInteractive":[992],"firstPaint":[1083],"fullyLoaded":[10796],"id":["180701_6G_A"],"loadTime":[2492],"render":[1500],"SpeedIndex":[1699],"TTFB":[670],"videoFrames":[[{"_i":"ms_000000.jpg","_t":0,"_vc":0},{"_i":"ms_001500.jpg","_t":1500,"_vc":83},{"_i":"ms_001600.jpg","_t":1600,"_vc":83},{"_i":"ms_001700.jpg","_t":1700,"_vc":83},{"_i":"ms_001800.jpg","_t":1800,"_vc":83},{"_i":"ms_001900.jpg","_t":1900,"_vc":83},{"_i":"ms_002000.jpg","_t":2000,"_vc":82},{"_i":"ms_002100.jpg","_t":2100,"_vc":82},{"_i":"ms_002200.jpg","_t":2200,"_vc":82},{"_i":"ms_002300.jpg","_t":2300,"_vc":82},{"_i":"ms_002400.jpg","_t":2400,"_vc":82},{"_i":"ms_002500.jpg","_t":2500,"_vc":88},{"_i":"ms_002700.jpg","_t":2700,"_vc":100}]],"visualComplete":[2700],"lighthouse":[null],"pagespeed":[100]}}