{"_ts":[1521736998,1521813453,1521899958,1521987753,1522075286,1522163111,1522249817,1522337295],"_r":{"breakdown":{"html":{"bytes":[0,0,0,0,0,0,0,0],"requests":[0,0,0,0,0,0,0,0]},"js":{"bytes":[0,0,0,0,0,0,0,0],"requests":[0,0,0,0,0,0,0,0]},"css":{"bytes":[0,0,0,0,0,0,0,0],"requests":[0,0,0,0,0,0,0,0]},"image":{"bytes":[0,0,0,0,0,0,0,0],"requests":[0,0,0,0,0,0,0,0]},"flash":{"bytes":[0,0,0,0,0,0,0,0],"requests":[0,0,0,0,0,0,0,0]},"font":{"bytes":[0,0,0,0,0,0,0,0],"requests":[0,0,0,0,0,0,0,0]},"other":{"bytes":[0,0,0,0,0,0,0,0],"requests":[1,1,1,1,1,1,1,1]}},"date":[1521736998,1521813453,1521899958,1521987753,1522075286,1522163111,1522249817,1522337295],"domElements":[null,null,null,null,null,null,null,null],"domInteractive":[null,null,null,null,null,null,null,null],"firstPaint":[null,null,null,null,null,null,null,null],"fullyLoaded":[null,null,null,null,null,null,null,null],"id":["180322_77_17","180323_XP_1E","180324_Z5_G","180325_JG_W","180326_0X_X","180327_HY_Y","180328_D4_P","180329_Q0_N"],"loadTime":[null,null,null,null,null,null,null,null],"render":[null,null,null,null,null,null,null,null],"SpeedIndex":[null,null,null,null,null,null,null,null],"TTFB":[null,null,null,null,null,null,null,null],"videoFrames":[[{"_i":"ms_000000.jpg","_t":0,"_vc":0},{"_i":"ms_031500.jpg","_t":31500,"_vc":100}],[{"_i":"ms_000000.jpg","_t":0,"_vc":0},{"_i":"ms_031500.jpg","_t":31500,"_vc":100}],[{"_i":"ms_000000.jpg","_t":0,"_vc":0},{"_i":"ms_031500.jpg","_t":31500,"_vc":100}],[{"_i":"ms_000000.jpg","_t":0,"_vc":0},{"_i":"ms_031500.jpg","_t":31500,"_vc":100}],[{"_i":"ms_000000.jpg","_t":0,"_vc":100}],[{"_i":"ms_000000.jpg","_t":0,"_vc":0},{"_i":"ms_031600.jpg","_t":31600,"_vc":100}],[{"_i":"ms_000000.jpg","_t":0,"_vc":0},{"_i":"ms_031400.jpg","_t":31400,"_vc":100}],[{"_i":"ms_000000.jpg","_t":0,"_vc":0},{"_i":"ms_031400.jpg","_t":31400,"_vc":100}]],"visualComplete":[null,null,null,null,null,null,null,null],"lighthouse":[null,null,null,null,null,null,null,null],"pagespeed":[null,null,null,null,null,null,null,null]}}