{"_ts":[1501555318],"_r":{"breakdown":{"html":{"bytes":[90096],"requests":[10]},"js":{"bytes":[895006],"requests":[22]},"css":{"bytes":[133465],"requests":[5]},"image":{"bytes":[694162],"requests":[35]},"flash":{"bytes":[0],"requests":[0]},"font":{"bytes":[116924],"requests":[6]},"other":{"bytes":[15603],"requests":[13]}},"date":[1501555318],"domElements":[1285.6666666666667],"domInteractive":[2486],"firstPaint":[2328.3333333333335],"fullyLoaded":[26165.666666666668],"id":["170801_S1_4"],"loadTime":[25968.666666666668],"render":[2580],"SpeedIndex":[3217.6666666666665],"TTFB":[157.33333333333334],"videoFrames":[[{"_i":"frame_0000.jpg","_t":0,"_vc":0},{"_i":"frame_0023.jpg","_t":2300,"_vc":52},{"_i":"frame_0034.jpg","_t":3400,"_vc":99},{"_i":"frame_0054.jpg","_t":5400,"_vc":99},{"_i":"frame_0114.jpg","_t":11400,"_vc":99},{"_i":"frame_0115.jpg","_t":11500,"_vc":99},{"_i":"frame_0117.jpg","_t":11700,"_vc":99},{"_i":"frame_0119.jpg","_t":11900,"_vc":99},{"_i":"frame_0121.jpg","_t":12100,"_vc":99},{"_i":"frame_0122.jpg","_t":12200,"_vc":99},{"_i":"frame_0124.jpg","_t":12400,"_vc":99},{"_i":"frame_0126.jpg","_t":12600,"_vc":99},{"_i":"frame_0127.jpg","_t":12700,"_vc":99},{"_i":"frame_0129.jpg","_t":12900,"_vc":99},{"_i":"frame_0151.jpg","_t":15100,"_vc":100},{"_i":"frame_0156.jpg","_t":15600,"_vc":99},{"_i":"frame_0202.jpg","_t":20200,"_vc":100},{"_i":"frame_0207.jpg","_t":20700,"_vc":99},{"_i":"frame_0250.jpg","_t":25000,"_vc":100}]],"visualComplete":[9253],"lighthouse":[null],"pagespeed":[null]}}