{"_ts":[1504797500,1504841198,1504884663],"_r":{"breakdown":{"html":{"bytes":[491838,500380,496839],"requests":[2,2,2]},"js":{"bytes":[400607,400584,400620],"requests":[10,10,10]},"css":{"bytes":[189208,189196,189208],"requests":[3,3,3]},"image":{"bytes":[41707,56434,52454],"requests":[17,24,22]},"flash":{"bytes":[0,0,0],"requests":[0,0,0]},"font":{"bytes":[61208,61208,61208],"requests":[3,3,3]},"other":{"bytes":[2749,2757,2749],"requests":[4,4,4]}},"date":[1504797500,1504841198,1504884663],"domElements":[1122.6666666666667,1303,1265.3333333333333],"domInteractive":[3435.3333333333335,3703,3444.3333333333335],"firstPaint":[2980.3333333333335,3223.3333333333335,2907.3333333333335],"fullyLoaded":[4685.333333333333,5175.666666666667,4602],"id":["170907_R6_C","170908_YA_J","170908_4J_17"],"loadTime":[4334.333333333333,4843.333333333333,4294.666666666667],"render":[3180.3333333333335,3379.6666666666665,3080.3333333333335],"SpeedIndex":[3240.3333333333335,3444,3138],"TTFB":[628.6666666666666,696.6666666666666,516.3333333333334],"videoFrames":[[{"_i":"frame_0000.jpg","_t":0,"_vc":0},{"_i":"frame_0032.jpg","_t":3200,"_vc":98},{"_i":"frame_0033.jpg","_t":3300,"_vc":98},{"_i":"frame_0035.jpg","_t":3500,"_vc":99},{"_i":"frame_0036.jpg","_t":3600,"_vc":99},{"_i":"frame_0038.jpg","_t":3800,"_vc":99},{"_i":"frame_0040.jpg","_t":4000,"_vc":99},{"_i":"frame_0042.jpg","_t":4200,"_vc":99},{"_i":"frame_0044.jpg","_t":4400,"_vc":99},{"_i":"frame_0045.jpg","_t":4500,"_vc":99},{"_i":"frame_0047.jpg","_t":4700,"_vc":99},{"_i":"frame_0049.jpg","_t":4900,"_vc":99},{"_i":"frame_0051.jpg","_t":5100,"_vc":99},{"_i":"frame_0053.jpg","_t":5300,"_vc":99},{"_i":"frame_0055.jpg","_t":5500,"_vc":99},{"_i":"frame_0056.jpg","_t":5600,"_vc":99},{"_i":"frame_0058.jpg","_t":5800,"_vc":99},{"_i":"frame_0060.jpg","_t":6000,"_vc":99},{"_i":"frame_0061.jpg","_t":6100,"_vc":99},{"_i":"frame_0062.jpg","_t":6200,"_vc":99},{"_i":"frame_0064.jpg","_t":6400,"_vc":99},{"_i":"frame_0066.jpg","_t":6600,"_vc":99},{"_i":"frame_0067.jpg","_t":6700,"_vc":99},{"_i":"frame_0068.jpg","_t":6800,"_vc":100}],[{"_i":"frame_0000.jpg","_t":0,"_vc":0},{"_i":"frame_0038.jpg","_t":3800,"_vc":98},{"_i":"frame_0039.jpg","_t":3900,"_vc":98},{"_i":"frame_0040.jpg","_t":4000,"_vc":98},{"_i":"frame_0041.jpg","_t":4100,"_vc":98},{"_i":"frame_0042.jpg","_t":4200,"_vc":98},{"_i":"frame_0043.jpg","_t":4300,"_vc":98},{"_i":"frame_0044.jpg","_t":4400,"_vc":98},{"_i":"frame_0045.jpg","_t":4500,"_vc":98},{"_i":"frame_0047.jpg","_t":4700,"_vc":98},{"_i":"frame_0048.jpg","_t":4800,"_vc":98},{"_i":"frame_0050.jpg","_t":5000,"_vc":99},{"_i":"frame_0051.jpg","_t":5100,"_vc":99},{"_i":"frame_0052.jpg","_t":5200,"_vc":99},{"_i":"frame_0053.jpg","_t":5300,"_vc":99},{"_i":"frame_0054.jpg","_t":5400,"_vc":99},{"_i":"frame_0056.jpg","_t":5600,"_vc":99},{"_i":"frame_0057.jpg","_t":5700,"_vc":99},{"_i":"frame_0058.jpg","_t":5800,"_vc":99},{"_i":"frame_0059.jpg","_t":5900,"_vc":99},{"_i":"frame_0060.jpg","_t":6000,"_vc":99},{"_i":"frame_0062.jpg","_t":6200,"_vc":99},{"_i":"frame_0063.jpg","_t":6300,"_vc":99},{"_i":"frame_0064.jpg","_t":6400,"_vc":99},{"_i":"frame_0065.jpg","_t":6500,"_vc":99},{"_i":"frame_0067.jpg","_t":6700,"_vc":99},{"_i":"frame_0069.jpg","_t":6900,"_vc":99},{"_i":"frame_0070.jpg","_t":7000,"_vc":99},{"_i":"frame_0072.jpg","_t":7200,"_vc":99},{"_i":"frame_0073.jpg","_t":7300,"_vc":99},{"_i":"frame_0074.jpg","_t":7400,"_vc":99},{"_i":"frame_0075.jpg","_t":7500,"_vc":99},{"_i":"frame_0076.jpg","_t":7600,"_vc":99},{"_i":"frame_0077.jpg","_t":7700,"_vc":99},{"_i":"frame_0078.jpg","_t":7800,"_vc":99},{"_i":"frame_0079.jpg","_t":7900,"_vc":100}],[{"_i":"frame_0000.jpg","_t":0,"_vc":0},{"_i":"frame_0032.jpg","_t":3200,"_vc":98},{"_i":"frame_0033.jpg","_t":3300,"_vc":99},{"_i":"frame_0035.jpg","_t":3500,"_vc":99},{"_i":"frame_0037.jpg","_t":3700,"_vc":99},{"_i":"frame_0038.jpg","_t":3800,"_vc":99},{"_i":"frame_0040.jpg","_t":4000,"_vc":99},{"_i":"frame_0041.jpg","_t":4100,"_vc":99},{"_i":"frame_0043.jpg","_t":4300,"_vc":99},{"_i":"frame_0045.jpg","_t":4500,"_vc":99},{"_i":"frame_0046.jpg","_t":4600,"_vc":99},{"_i":"frame_0048.jpg","_t":4800,"_vc":99},{"_i":"frame_0049.jpg","_t":4900,"_vc":99},{"_i":"frame_0051.jpg","_t":5100,"_vc":99},{"_i":"frame_0053.jpg","_t":5300,"_vc":99},{"_i":"frame_0054.jpg","_t":5400,"_vc":99},{"_i":"frame_0056.jpg","_t":5600,"_vc":99},{"_i":"frame_0058.jpg","_t":5800,"_vc":99},{"_i":"frame_0059.jpg","_t":5900,"_vc":99},{"_i":"frame_0060.jpg","_t":6000,"_vc":99},{"_i":"frame_0062.jpg","_t":6200,"_vc":99},{"_i":"frame_0063.jpg","_t":6300,"_vc":99},{"_i":"frame_0065.jpg","_t":6500,"_vc":99},{"_i":"frame_0066.jpg","_t":6600,"_vc":100}]],"visualComplete":[6733.333333333333,7233.333333333333,6700],"lighthouse":[null,null,null],"pagespeed":[100,100,100]}}